Metadata-Version: 2.1
Name: AWS-IFG-distributions
Version: 1.0
Summary: Gaussian and Binomial distributions
Home-page: UNKNOWN
Author: Ivan F. Gonzalez
Author-email: datascience@ivanfgonzalez.com
License: UNKNOWN
Platform: UNKNOWN
